FULL_ADDER_SWITCH_LEVEL_MODEL_design.sv
module fulladder (cout, sum, a, b, cin);
    output cout, sum;
    input a, b, cin;
    wire w1, w2, w3, w4, w5, w6, w7, w8, w9, w10, w11, w12, w13, w14, w15, w16, w17;
    supply1 VDD;
    supply0 GND;

    //SUM
    pmos p1 (w1, VDD, a);
    pmos p2 (w3, w1, b);
    pmos p3 (sum, w3, w17);
    pmos p4 (w4, w1, w16);
    pmos p5 (sum, w4, cin);
    pmos p6 (w2, VDD, w15);
    pmos p7 (w5, w2, b);
    pmos p8 (sum, w5, cin);
    pmos p9 (w6, w2, w16);
    pmos p10 (sum, w6, w17);

    nmos n1 (sum, w8, a);
    nmos n2 (sum, w7, b);
    nmos n3 (sum, w7, w17);
    nmos n4 (w7, w8, w16);
    nmos n5 (w7, w8, cin);
    nmos n6 (w8, GND, w15);
    nmos n7 (w8, w9, b);
    nmos n8 (w8, w9, cin);
    nmos n9 (w9, GND, w16);
    nmos n10 (w9, GND, w17);

    // CARRY
    pmos p11 (w10, VDD, w15);
    pmos p12 (cout, w10, w16);
    pmos p13 (w11, VDD, w16);
    pmos p14 (cout, w11, w17);
    pmos p15 (w12, VDD, w17);
    pmos p16 (cout, w12, w15);

    nmos n11 (cout, w13, w15);
    nmos n12 (cout, w13, w16);
    nmos n13 (w13, w14, w16);
    nmos n14 (w13, w14, w17);
    nmos n15 (w14, GND, w17);
    nmos n16 (w14, GND, w15);

    // NOT A
    pmos p17 (w15, VDD, a);
    nmos n17 (w15, GND, a);

    // NOT B
    pmos p18 (w16, VDD, b);
    nmos n18 (w16, GND, b);

    // NOT CIN
    pmos p19 (w17, VDD, cin);
    nmos n19 (w17, GND, cin);

endmodule

FULL_ADDER_testbench.sv
`timescale 1ns / 1ps

module tb_universal_fulladder;
    reg a, b, cin;
    wire sum, cout;
  
    fulladder uut (
        .cout(cout),
        .sum(sum),
        .a(a),
        .b(b),
        .cin(cin)
    );

    //  Stimulus 
    initial begin
        // Files for waveform viewing (EPWave / GTKWave)
        $dumpfile("dump.vcd");
        $dumpvars(0, tb_universal_fulladder);

        // Header for the console log
        $display("Time\t a b cin | sum cout");
        $monitor("%0t\t %b %b  %b  |  %b    %b", $time, a, b, cin, sum, cout);

        // Test all 8 possible input combinations
        {a, b, cin} = 3'b000; #10;
        {a, b, cin} = 3'b001; #10;
        {a, b, cin} = 3'b010; #10;
        {a, b, cin} = 3'b011; #10;
        {a, b, cin} = 3'b100; #10;
        {a, b, cin} = 3'b101; #10;
        {a, b, cin} = 3'b110; #10;
        {a, b, cin} = 3'b111; #10;

        $display("Simulation Task Completed.");
        $finish;
    end

endmodule

dump.vcd
$date
	Tue Mar 17 04:25:06 2026
$end
$version
	Icarus Verilog
$end
$timescale
	1ps
$end
$scope module tb_universal_fulladder $end
$var wire 1 ! cout $end
$var wire 1 " sum $end
$var reg 1 # a $end
$var reg 1 $ b $end
$var reg 1 % cin $end
$scope module uut $end
$var wire 1 & GND $end
$var wire 1 ' VDD $end
$var wire 1 # a $end
$var wire 1 $ b $end
$var wire 1 % cin $end
$var wire 1 ! cout $end
$var wire 1 " sum $end
$var wire 1 ( w1 $end
$var wire 1 ) w10 $end
$var wire 1 * w11 $end
$var wire 1 + w12 $end
$var wire 1 , w13 $end
$var wire 1 - w14 $end
$var wire 1 . w15 $end
$var wire 1 / w16 $end
$var wire 1 0 w17 $end
$var wire 1 1 w2 $end
$var wire 1 2 w3 $end
$var wire 1 3 w4 $end
$var wire 1 4 w5 $end
$var wire 1 5 w6 $end
$var wire 1 6 w7 $end
$var wire 1 7 w8 $end
$var wire 1 8 w9 $end
$upscope $end
$upscope $end
$enddefinitions $end
$comment Show the parameter values. $end
$dumpall
$end
#0
$dumpvars
08
07
06
z5
z4
z3
12
z1
10
1/
1.
0-
0,
z+
z*
z)
1(
1'
0&
0%
0$
0#
0"
0!
$end
#10000
1"
1+
00
1%
#20000
z2
z4
13
z5
z6
1*
0/
1$
1"
z+
10
0%
#30000
0"
06
z8
1+
1!
z,
00
1%
#40000
z(
11
z7
1)
0.
1#
z2
14
z3
z5
z*
1/
0$
1"
z6
08
z+
0!
0,
10
0%
#50000
0"
06
07
1+
1!
z,
z-
00
1%
#60000
z2
z4
z3
15
1*
0/
1$
0"
z6
07
z+
1!
0,
0-
10
0%
#70000
1"
z7
z8
1+
z,
z-
00
1%
